valthera/__init__.py
valthera/agent.py
valthera/aggregator.py
valthera/connectors/__init__.py
valthera/connectors/base.py
valthera/connectors/builtin/__init__.py
valthera/connectors/builtin/hubspot.py
valthera/connectors/builtin/posthog.py
valthera/connectors/builtin/snowflake.py
valthera/connectors/generic_api_connector.py
valthera/connectors/generic_sql_connector.py
valthera/models.py
valthera/reasoning_engine.py
valthera/scorer.py
valthera/trigger_generator.py
valthera-0.1.2.dist-info/METADATA
valthera-0.1.2.dist-info/WHEEL
valthera-0.1.2.dist-info/RECORD
