Metadata-Version: 2.1
Name: valthera
Version: 0.1.2
Summary: 
Author: Vijay Selvaraj
Author-email: vijay.selvaraj@gmail.com
Requires-Python: >=3.9,<4.0
Classifier: Programming Language :: Python :: 3
Classifier: Programming Language :: Python :: 3.9
Classifier: Programming Language :: Python :: 3.10
Classifier: Programming Language :: Python :: 3.11
Classifier: Programming Language :: Python :: 3.12
Classifier: Programming Language :: Python :: 3.13
Requires-Dist: hubspot-api-client (>=11.1.0,<12.0.0)
Requires-Dist: langchain-community (>=0.3.18,<0.4.0)
Requires-Dist: langchain-core (>=0.3.40,<0.4.0)
Requires-Dist: openai (>=1.65.2,<2.0.0)
